<annotation>
	<folder>train</folder>
	<filename>228.png</filename>
	<path>/home/atulu/Documents/cav_detection_tf_obj_det_api/models/research/object_detection/legacy/imgs/train/228.png</path>
	<source>
		<database>Unknown</database>
	</source>
	<size>
		<width>600</width>
		<height>435</height>
		<depth>3</depth>
	</size>
	<segmented>0</segmented>
	<object>
		<name>decay/cavity</name>
		<pose>Unspecified</pose>
		<truncated>0</truncated>
		<difficult>0</difficult>
		<bndbox>
			<xmin>396</xmin>
			<ymin>135</ymin>
			<xmax>475</xmax>
			<ymax>196</ymax>
		</bndbox>
	</object>
	<object>
		<name>decay/cavity</name>
		<pose>Unspecified</pose>
		<truncated>0</truncated>
		<difficult>0</difficult>
		<bndbox>
			<xmin>194</xmin>
			<ymin>208</ymin>
			<xmax>337</xmax>
			<ymax>334</ymax>
		</bndbox>
	</object>
</annotation>
